sais/__init__.py
sais/autotrain/__init__.py
sais/autotrain/dataservice/__init__.py
sais/autotrain/dataservice/auth/__init__.py
sais/autotrain/dataservice/auth/auth_info.py
sais/autotrain/dataservice/cfg/__init__.py
sais/autotrain/dataservice/cfg/env.py
sais/autotrain/dataservice/client/__init__.py
sais/autotrain/dataservice/client/mongo_client.py
sais/autotrain/dataservice/client/redis_client.py
sais/autotrain/dataservice/config/__init__.py
sais/autotrain/dataservice/config/const.py
sais/autotrain/dataservice/config/mongo_config.py
sais/autotrain/dataservice/config/version.py
sais/autotrain/dataservice/handler/__init__.py
sais/autotrain/dataservice/handler/query_handler.py
sais/autotrain/dataservice/handler/train_infer_handler.py
sais/autotrain/dataservice/model/__init__.py
sais/autotrain/dataservice/model/data_model.py
sais/autotrain/dataservice/model/train_infer_model.py
sais/autotrain/dataservice/mytest/__init__.py
sais/autotrain/dataservice/mytest/query_test.py
sais/autotrain/dataservice/types/__init__.py
sais/autotrain/dataservice/types/biz_exception.py
sais/autotrain/dataservice/types/error_enum.py
data_service_sdk-0.0.41.dist-info/METADATA
data_service_sdk-0.0.41.dist-info/WHEEL
data_service_sdk-0.0.41.dist-info/RECORD
