Metadata-Version: 2.4
Name: data-service-sdk
Version: 0.0.41
Summary: data-service-sdk python sdk
Project-URL: repository, https://github.com/xxx/xxxx
Author: SAIS Contributors
Author-email: sais@example.com
License: Apache License 2.0
Keywords: auto train data service,sais
Classifier: Programming Language :: Python :: 3.9
Classifier: Topic :: Software Development :: Libraries
Classifier: Topic :: Software Development :: Libraries :: Python Modules
Requires-Python: >=3.9
Requires-Dist: loguru
Requires-Dist: pandas
Requires-Dist: pydantic~=2.7.4
Requires-Dist: pymongo
Requires-Dist: requests~=2.32.3
Requires-Dist: setuptools~=69.5.1
Provides-Extra: test
